README.md
setup.py
tunable/__init__.py
tunable/modulehelper.py
tunable/selectable.py
tunable/tunable.py
tunable/tunablemanager.py
tunable/tunableselectable.py
tunable.egg-info/PKG-INFO
tunable.egg-info/SOURCES.txt
tunable.egg-info/dependency_links.txt
tunable.egg-info/requires.txt
tunable.egg-info/top_level.txt
tunable/schema/__init__.py
tunable/schema/tunable_schema.asn
tunable/schema/tunable_schema.py