Metadata-Version: 1.1
Name: tunable
Version: 0.0.1.dev5
Summary: tunable manager
Home-page: https://github.com/csachs/tunable
Author: Christian C. Sachs
Author-email: sachs.christian@gmail.com
License: MIT
Platform: UNKNOWN
Classifier: Development Status :: 4 - Beta
Classifier: License :: OSI Approved :: MIT License
Classifier: Programming Language :: Python :: 3
